huaweicloudsdkcodeartsgovernance/__init__.py
huaweicloudsdkcodeartsgovernance/v1/__init__.py
huaweicloudsdkcodeartsgovernance/v1/codeartsgovernance_async_client.py
huaweicloudsdkcodeartsgovernance/v1/codeartsgovernance_client.py
huaweicloudsdkcodeartsgovernance/v1/model/__init__.py
huaweicloudsdkcodeartsgovernance/v1/model/action_with_entities.py
huaweicloudsdkcodeartsgovernance/v1/model/apk_component_info.py
huaweicloudsdkcodeartsgovernance/v1/model/apk_component_item.py
huaweicloudsdkcodeartsgovernance/v1/model/basic_info.py
huaweicloudsdkcodeartsgovernance/v1/model/create_sec_app_task_request.py
huaweicloudsdkcodeartsgovernance/v1/model/create_sec_app_task_request_body.py
huaweicloudsdkcodeartsgovernance/v1/model/create_sec_app_task_response.py
huaweicloudsdkcodeartsgovernance/v1/model/delete_sec_app_task_request.py
huaweicloudsdkcodeartsgovernance/v1/model/delete_sec_app_task_response.py
huaweicloudsdkcodeartsgovernance/v1/model/hap_component_info.py
huaweicloudsdkcodeartsgovernance/v1/model/hap_component_item.py
huaweicloudsdkcodeartsgovernance/v1/model/hm_vuln_info_data.py
huaweicloudsdkcodeartsgovernance/v1/model/hm_vuln_info_data_detail.py
huaweicloudsdkcodeartsgovernance/v1/model/hm_vuln_info_data_detail_vuln_info.py
huaweicloudsdkcodeartsgovernance/v1/model/hm_vuln_info_data_report.py
huaweicloudsdkcodeartsgovernance/v1/model/operate_info_response_body.py
huaweicloudsdkcodeartsgovernance/v1/model/permission_item.py
huaweicloudsdkcodeartsgovernance/v1/model/privacy_compliance_info.py
huaweicloudsdkcodeartsgovernance/v1/model/privacy_compliance_subtype.py
huaweicloudsdkcodeartsgovernance/v1/model/show_hm_report_request.py
huaweicloudsdkcodeartsgovernance/v1/model/show_hm_report_response.py
huaweicloudsdkcodeartsgovernance/v1/model/show_sec_app_task_result_request.py
huaweicloudsdkcodeartsgovernance/v1/model/show_sec_app_task_result_response.py
huaweicloudsdkcodeartsgovernance/v1/model/show_sec_app_task_status_request.py
huaweicloudsdkcodeartsgovernance-3.1.184.dist-info/METADATA
huaweicloudsdkcodeartsgovernance-3.1.184.dist-info/WHEEL
huaweicloudsdkcodeartsgovernance-3.1.184.dist-info/licenses/LICENSE
huaweicloudsdkcodeartsgovernance-3.1.184.dist-info/RECORD
